usachev/__init__.py
usachev/checkers/__init__.py
usachev/checkers/print_checker.py
usachev_pylint_checkers-0.1.dist-info/LICENSE
usachev_pylint_checkers-0.1.dist-info/METADATA
usachev_pylint_checkers-0.1.dist-info/WHEEL
usachev_pylint_checkers-0.1.dist-info/top_level.txt
usachev_pylint_checkers-0.1.dist-info/RECORD
