Metadata-Version: 2.1
Name: usachev-pylint-checkers
Version: 0.1
Summary: A library provides pylint checkers.
Home-page: https://github.com/NightFantom/usachev_pylint_checkers
Author: Denis Usachev
Author-email: usachevdy@yandex.ru
License: UNKNOWN
Platform: UNKNOWN
Classifier: Programming Language :: Python :: 3
Classifier: Operating System :: OS Independent
Requires-Python: >=3.6
